{
  "version": "7",
  "dialect": "postgresql",
  "entries": [
    {
      "idx": 0,
      "version": "7",
      "when": 1733524499177,
      "tag": "0000_eager_lilith",
      "breakpoints": true
    },
    {
      "idx": 1,
      "version": "7",
      "when": 1737001892655,
      "tag": "0001_hot_loners",
      "breakpoints": true
    },
    {
      "idx": 2,
      "version": "7",
      "when": 1737142922146,
      "tag": "0002_graceful_cargill",
      "breakpoints": true
    },
    {
      "idx": 3,
      "version": "7",
      "when": 1737144757810,
      "tag": "0003_brave_namora",
      "breakpoints": true
    }
  ]
}
